Metadata-Version: 2.1
Name: excel-1drive-noPassword
Version: 1.2.4
Summary: Package to download and manipulate Excel files from OneDrive URLs that are set to *accessible by anyone with the URL*
Home-page: https://github.com/abhishekvenkat764/excel_1drive_noPassword
Author: Abhishek Venkatachalam
Author-email: abhishek.venkatachalam06@gmail.com
Classifier: Programming Language :: Python :: 3
Classifier: License :: OSI Approved :: GNU General Public License v3 or later (GPLv3+)
Classifier: Operating System :: OS Independent
Requires-Python: >=3.7
License-File: LICENSE
